swagger_client/__init__.py
swagger_client/api_client.py
swagger_client/configuration.py
swagger_client/rest.py
swagger_client/api/__init__.py
swagger_client/api/accounts_api.py
swagger_client/api/comments_api.py
swagger_client/api/custom_fields_api.py
swagger_client/api/default_api.py
swagger_client/api/documentation_api.py
swagger_client/api/draft_tickets_api.py
swagger_client/api/forms_api.py
swagger_client/api/organizations_api.py
swagger_client/api/reactions_api.py
swagger_client/api/tags_api.py
swagger_client/api/teams_api.py
swagger_client/api/ticket_tags_api.py
swagger_client/api/tickets_api.py
swagger_client/api/users_api.py
swagger_client/api/views_api.py
swagger_client/api/views_types_api.py
swagger_client/models/__init__.py
swagger_client/models/account_activity_response_dto.py
swagger_client/models/account_attribute_value_response_dto.py
swagger_client/models/account_note_response_dto.py
swagger_client/models/account_relationship_response_dto.py
swagger_client/models/account_relationship_type_response_dto.py
swagger_client/models/account_response_dto.py
swagger_client/models/account_task_response_dto.py
swagger_client/models/add_reaction_dto.py
swagger_client/models/add_tags_dto.py
swagger_client/models/add_team_member_dto.py
swagger_client/models/all_of_account_relationship_response_dto_relationship_type.py
swagger_client/models/all_of_business_days_friday.py
swagger_client/models/all_of_business_days_monday.py
swagger_client/models/all_of_business_days_saturday.py
swagger_client/models/all_of_business_days_sunday.py
swagger_client/models/all_of_business_days_thursday.py
swagger_client/models/all_of_business_days_tuesday.py
swagger_client/models/all_of_business_days_wednesday.py
swagger_client/models/all_of_business_hours_config_dto_friday.py
swagger_client/models/all_of_business_hours_config_dto_monday.py
swagger_client/models/all_of_business_hours_config_dto_saturday.py
swagger_client/models/all_of_business_hours_config_dto_sunday.py
thena_platform_client-1.0.0.dist-info/METADATA
thena_platform_client-1.0.0.dist-info/WHEEL
thena_platform_client-1.0.0.dist-info/top_level.txt
thena_platform_client-1.0.0.dist-info/RECORD
